xmsinterp/__init__.py
xmsinterp/_xmsinterp.cp36-win_amd64.pyd
xmsinterp/interpolate/__init__.py
xmsinterp/interpolate/interp_anisotropic.py
xmsinterp/interpolate/interp_idw.py
xmsinterp/interpolate/interp_linear.py
xmsinterp-3.0.1.dist-info/METADATA
xmsinterp-3.0.1.dist-info/WHEEL
xmsinterp-3.0.1.dist-info/top_level.txt
xmsinterp-3.0.1.dist-info/RECORD
